README.txt
setup.cfg
setup.py
rocksolid_agent/LICENSE.txt
rocksolid_agent/__init__.py
rocksolid_agent/rocksolid-agent.cat
rocksolid_agent/rocksolid-agent.def
rocksolid_agent/rocksolid_agent.py
rocksolid_agent.egg-info/PKG-INFO
rocksolid_agent.egg-info/SOURCES.txt
rocksolid_agent.egg-info/dependency_links.txt
rocksolid_agent.egg-info/entry_points.txt
rocksolid_agent.egg-info/top_level.txt
rocksolid_agent/libs/__init__.py
rocksolid_agent/libs/__init__.pyc
rocksolid_agent/libs/base.py
rocksolid_agent/libs/fil.py
rocksolid_agent/libs/lmd.py
rocksolid_agent/libs/mat.py
rocksolid_agent/libs/mod.py
rocksolid_agent/libs/pac.py
rocksolid_agent/libs/prt.py