Metadata-Version: 1.1
Name: rocksolid-agent
Version: 1.0.17
Summary: rocksolid security agent. Find and mitigate outdated software/apps on your server
Home-page: https://github.com/rocksolid-io/rocksolid-agent
Author: rocksolid
Author-email: hello@rocksolid.io
License: UNKNOWN
Download-URL: https://github.com/rocksolid-io/rocksolid-agent/tarball/1.0.17
Keywords: rocksolid,agent,scan,security,cms,packages,vulnerability
Platform: UNKNOWN
